orlax/__init__.py
orlax/algos/__init__.py
orlax/algos/bc.py
orlax/algos/cql.py
orlax/algos/iql.py
orlax/core/__init__.py
orlax/core/buffer.py
orlax/core/cfg.py
orlax/core/logger.py
orlax/core/optim.py
orlax/core/types.py
orlax/core/utils.py
orlax/data/__init__.py
orlax/data/collate.py
orlax/data/dataset.py
orlax/data/minari.py
orlax/models/__init__.py
orlax/models/mlp.py
orlax/models/nets.py
orlax/py.typed
orlax/scripts/eval.py
orlax/scripts/export.py
orlax/scripts/run.py
orlax/train/__init__.py
orlax/train/loop.py
orlax/train/pmap.py
orlax/train/runner.py
orlax-0.1.1.dist-info/WHEEL
orlax-0.1.1.dist-info/entry_points.txt
orlax-0.1.1.dist-info/METADATA
orlax-0.1.1.dist-info/RECORD
