Metadata-Version: 2.3
Name: orlax
Version: 0.1.1
Summary: Extensible offline reinforcement learning framework built with JAX, Flax, and Optax
Author: sql-hkr
Author-email: sql-hkr <sql.hkr@gmail.com>
Classifier: License :: OSI Approved :: MIT License
Classifier: Programming Language :: Python :: 3.11
Requires-Dist: jax>=0.4.20
Requires-Dist: jaxlib>=0.4.20
Requires-Dist: flax>=0.7.5
Requires-Dist: optax>=0.1.7
Requires-Dist: wandb>=0.16.0
Requires-Dist: tqdm>=4.66.0
Requires-Dist: numpy>=1.24.0
Requires-Dist: distrax>=0.1.5
Requires-Dist: setuptools>=80.9.0
Requires-Dist: mujoco==3.2.3
Requires-Dist: minari[all]>=0.5.3
Requires-Dist: pillow>=11.3.0
Requires-Dist: imageio>=2.37.2
Requires-Dist: matplotlib>=3.9.4
Requires-Dist: gymnasium-robotics>=1.2.3
Requires-Python: >=3.11
